Metadata-Version: 1.0
Name: Products.Quaestrio
Version: 0.13.1
Summary: A quizz product sponsorised by Makina Corpus
Home-page: https://svn.plone.org/svn/collective/Products.Quaestrio
Author: Mathieu Pasquet
Author-email: mpa@makina-corpus.com
License: GPL
Keywords: plone guerir.fr
Platform: UNKNOWN
Classifier: Framework :: Plone
Classifier: Programming Language :: Python
Classifier: Topic :: Software Development :: Libraries :: Python Modules
